mcpx_py/__init__.py
mcpx_py/__main__.py
mcpx_py/chat.py
mcpx_py-0.7.0.dist-info/METADATA
mcpx_py-0.7.0.dist-info/WHEEL
mcpx_py-0.7.0.dist-info/entry_points.txt
mcpx_py-0.7.0.dist-info/top_level.txt
mcpx_py-0.7.0.dist-info/RECORD
