Metadata-Version: 2.4
Name: mcpx-py
Version: 0.7.0
Summary: An mcp.run client for Python
Requires-Python: >=3.12
Requires-Dist: mcpx-pydantic-ai>=0.7.0
Requires-Dist: psutil>=7.0.0
Requires-Dist: python-dotenv>=1.0.1
